{
  "hash": "739e9daa",
  "configHash": "0a53b707",
  "lockfileHash": "02721eea",
  "browserHash": "497047bc",
  "optimized": {
    "react": {
      "src": "../../node_modules/react/index.js",
      "file": "react.js",
      "fileHash": "68478e8a",
      "needsInterop": true
    },
    "react-dom/client": {
      "src": "../../node_modules/react-dom/client.js",
      "file": "react-dom_client.js",
      "fileHash": "d92a60ae",
      "needsInterop": true
    },
    "react-router-dom": {
      "src": "../../node_modules/react-router-dom/dist/index.mjs",
      "file": "react-router-dom.js",
      "fileHash": "ac48fb3d",
      "needsInterop": false
    }
  },
  "chunks": {
    "chunk-QOVZGY7A": {
      "file": "chunk-QOVZGY7A.js"
    },
    "chunk-5WQJO2FO": {
      "file": "chunk-5WQJO2FO.js"
    }
  }
}